[{
"id": "ID_0190be5d-a551-4890-b34e-5ce7817c6816",
"qualifiedName": "/GISA/CCLM./GISA/CCLMT./GISA/CCLMT_CROSSREF_TEST./GISA/CCLMT_CR_TEST_REPORT_02",
"name": "/GISA/CCLMT_CR_TEST_REPORT_02",
"abap_type": "REPS",
"type": "Report",
"creator": "GPRA437",
"created": 20200915,
"changed_by": "GPRA437",
"changed": 20200915,
"iteration": 0,
"number_of_statements": 3,
"container_id": 2,
"belongsTo": "ID_76417dc0-9f5e-484f-b6ef-91c6ec617092",
"calls": "ID_d14d053b-b686-4683-ac06-19a4a76b6560, ID_3c9218a4-31f0-4371-8554-2e8a0a7db97e",
"calledBy": ""
},{
"id": "ID_061e8f94-a038-4092-bd15-be9a8ff6a78a",
"qualifiedName": "/GISA/CCLM./GISA/CCLMT./GISA/CCLMT_CROSSREF_TEST./GISA/CL_CCLMT_CR_TEST_CLASS01.TEST_METHOD06",
"name": "TEST_METHOD06",
"abap_type": "METH",
"type": "Method",
"creator": "GPRA437",
"created": 20200915,
"changed_by": "GPRA587",
"changed": 20220110,
"iteration": 0,
"number_of_statements": 1,
"container_id": 1,
"belongsTo": "ID_3c9218a4-31f0-4371-8554-2e8a0a7db97e",
"calls": "ID_6dc6d9e6-4853-47c3-a8e9-5cf62c28394a",
"calledBy": "ID_add55f0a-0cf5-4f1f-889a-065c36a5edf9",
"signature": ""
},{
"id": "ID_07681bde-445d-4a93-97a8-7e1f5d60594d",
"qualifiedName": "/GISA/CCLM./GISA/CCLMT./GISA/CCLMT_CROSSREF_TEST./GISA/CCLMT_CR_TEST_REPORT_03",
"name": "/GISA/CCLMT_CR_TEST_REPORT_03",
"abap_type": "REPS",
"type": "Report",
"creator": "GPRA437",
"created": 20200916,
"changed_by": "GPRA437",
"changed": 20200916,
"iteration": 0,
"number_of_statements": 2,
"container_id": 2,
"belongsTo": "ID_76417dc0-9f5e-484f-b6ef-91c6ec617092",
"calls": "ID_bfb0b45b-1916-40ab-97fe-0afdc8e8890d",
"calledBy": ""
},{
"id": "ID_09b15d34-6c25-49ee-b017-96f947273989",
"qualifiedName": "/GISA/CCLM./GISA/CCLMT./GISA/CCLMT_CROSSREF_TEST./GISA/CL_CCLMT_CR_TEST_CLASS03.DYNAMIC_TEST_METHOD03",
"name": "DYNAMIC_TEST_METHOD03",
"abap_type": "METH",
"type": "Method",
"creator": "GPRA437",
"created": 20201117,
"changed_by": "GPRA437",
"changed": 20201202,
"iteration": 0,
"number_of_statements": 4,
"container_id": 41,
"belongsTo": "ID_7f8d04ed-63ba-45c9-8146-8034ffde21ae",
"calls": "ID_3c9218a4-31f0-4371-8554-2e8a0a7db97e",
"calledBy": "",
"signature": ""
},{
"id": "ID_09d08532-3963-4fff-8516-a0e1c69b35b1",
"qualifiedName": "/GISA/CCLM./GISA/CCLMT./GISA/CCLMT_CROSSREF_TEST./GISA/CCLMT_CR_TEST_REPORT_03",
"name": "/GISA/CCLMT_CR_TEST_REPORT_03",
"abap_type": "REPS",
"type": "Report",
"creator": "GPRA437",
"created": 20200916,
"changed_by": "GPRA437",
"changed": 20200916,
"iteration": 0,
"number_of_statements": 2,
"container_id": 2,
"belongsTo": "ID_07681bde-445d-4a93-97a8-7e1f5d60594d",
"calls": "ID_bfb0b45b-1916-40ab-97fe-0afdc8e8890d",
"calledBy": ""
},{
"id": "ID_0d9391f0-d454-4380-a758-16fe6fcfcb0f",
"qualifiedName": "/GISA/CCLM./GISA/CCLMT./GISA/CCLMT_CROSSREF_TEST./GISA/CL_CCLMT_CR_TEST_CLASS03.DYNAMIC_TEST_METHOD02",
"name": "DYNAMIC_TEST_METHOD02",
"abap_type": "METH",
"type": "Method",
"creator": "GPRA437",
"created": 20201117,
"changed_by": "GPRA437",
"changed": 20201202,
"iteration": 0,
"number_of_statements": 3,
"container_id": 41,
"belongsTo": "ID_7f8d04ed-63ba-45c9-8146-8034ffde21ae",
"calls": "ID_23a16a9a-9d4b-406a-84a9-e344c2bde655, ID_3c9218a4-31f0-4371-8554-2e8a0a7db97e",
"calledBy": "",
"signature": ""
},{
"id": "ID_23a16a9a-9d4b-406a-84a9-e344c2bde655",
"qualifiedName": "/GISA/CCLM./GISA/CCLMT./GISA/CCLMT_CROSSREF_TEST./GISA/CL_CCLMT_CR_TEST_CLASS01.TEST_METHOD02",
"name": "TEST_METHOD02",
"abap_type": "METH",
"type": "Method",
"creator": "GPRA437",
"created": 20200915,
"changed_by": "GPRA587",
"changed": 20220110,
"iteration": 0,
"number_of_statements": 3,
"container_id": 1,
"belongsTo": "ID_3c9218a4-31f0-4371-8554-2e8a0a7db97e",
"calls": "ID_d14d053b-b686-4683-ac06-19a4a76b6560",
"calledBy": "ID_e30bc010-ada2-4a9a-b8a9-16bb5f9facb0, ID_0d9391f0-d454-4380-a758-16fe6fcfcb0f",
"signature": ""
},{
"id": "ID_267b8871-93bf-4ff9-ad17-ca1c78e0ee73",
"qualifiedName": "LCL_WIND",
"name": "LCL_WIND",
"abap_type": "CLAS",
"type": "Class",
"creator": "GPRA587",
"created": 20220303,
"changed_by": "GPRA587",
"changed": 20220303,
"iteration": 0,
"local_class": "true",
"uses_id": 109,
"belongsTo": "ID_6c7e4196-d4cc-4cbe-923b-a1c717569219",
"subClassOf": "",
"superClassOf": ""
},{
"id": "ID_26f2d17c-c346-4312-a73f-78d91c0ee71b",
"qualifiedName": "/GISA/CCLM./GISA/CCLMT./GISA/CCLMT_CROSSREF_TEST./GISA/CCLMT_CR_TEST_REPORT_03.LO_TEST",
"name": "LO_TEST",
"abap_type": "ATTR",
"type": "Attribute",
"creator": "GPRA437",
"created": 20200916,
"changed_by": "GPRA437",
"changed": 20200916,
"iteration": 0,
"container_id": 87,
"belongsTo": "ID_07681bde-445d-4a93-97a8-7e1f5d60594d"
},{
"id": "ID_275d6dab-bbb1-4740-8fc9-2b95fe23942c",
"qualifiedName": "/GISA/CCLM./GISA/CCLMT./GISA/CCLMT_CROSSREF_TEST./GISA/CL_CCLMT_CR_TEST_CLASS03.DYNAMIC_TEST_METHOD04",
"name": "DYNAMIC_TEST_METHOD04",
"abap_type": "METH",
"type": "Method",
"creator": "GPRA437",
"created": 20201117,
"changed_by": "GPRA437",
"changed": 20201202,
"iteration": 0,
"number_of_statements": 4,
"container_id": 41,
"belongsTo": "ID_7f8d04ed-63ba-45c9-8146-8034ffde21ae",
"calls": "ID_a6c3c4d2-751e-4193-b2d6-d42742e9262b, ID_3c9218a4-31f0-4371-8554-2e8a0a7db97e",
"calledBy": "",
"signature": ""
},{
"id": "ID_3c9218a4-31f0-4371-8554-2e8a0a7db97e",
"qualifiedName": "/GISA/CCLM./GISA/CCLMT./GISA/CCLMT_CROSSREF_TEST./GISA/CL_CCLMT_CR_TEST_CLASS01",
"name": "/GISA/CL_CCLMT_CR_TEST_CLASS01",
"abap_type": "CLAS",
"type": "Class",
"creator": "GPRA437",
"created": 20200915,
"changed_by": "GPRA587",
"changed": 20220110,
"iteration": 0,
"local_class": "false",
"container_id": 2,
"belongsTo": "ID_76417dc0-9f5e-484f-b6ef-91c6ec617092",
"subClassOf": "",
"superClassOf": ""
},{
"id": "ID_4126ad2f-d853-4eee-b252-c41999cee2d5",
"qualifiedName": "LCL_WIND",
"name": "LCL_WIND",
"abap_type": "CLAS",
"type": "Class",
"creator": "GPRA587",
"created": 20220303,
"changed_by": "GPRA587",
"changed": 20220303,
"iteration": 0,
"local_class": "true",
"uses_id": 100,
"belongsTo": "ID_ac399c5c-3623-4cc4-b06b-f1636b057403",
"subClassOf": "",
"superClassOf": ""
},{
"id": "ID_4a02540f-5d15-4200-88e2-b35c51feb5fb",
"qualifiedName": "/GISA/CCLM./GISA/CCLMT./GISA/CCLMT_CROSSREF_TEST./GISA/CL_CCLMT_CR_TEST_CLASS03.DYNAMIC_TEST_METHOD05",
"name": "DYNAMIC_TEST_METHOD05",
"abap_type": "METH",
"type": "Method",
"creator": "GPRA437",
"created": 20201117,
"changed_by": "GPRA437",
"changed": 20201202,
"iteration": 0,
"number_of_statements": 6,
"container_id": 41,
"belongsTo": "ID_7f8d04ed-63ba-45c9-8146-8034ffde21ae",
"calls": "ID_3c9218a4-31f0-4371-8554-2e8a0a7db97e, ID_c6c58ab4-ad16-4c87-9c87-fe229d3b0f1c",
"calledBy": "",
"signature": ""
},{
"id": "ID_4af5f5bf-41ec-431c-9cec-16f8fafad58a",
"qualifiedName": "/GISA/CCLM./GISA/CCLMT./GISA/CCLMT_CROSSREF_TEST./GISA/CL_CCLMT_CR_TEST_CLASS01.LOOP_METHOD01",
"name": "LOOP_METHOD01",
"abap_type": "METH",
"type": "Method",
"creator": "GPRA437",
"created": 20200915,
"changed_by": "GPRA587",
"changed": 20220110,
"iteration": 0,
"number_of_statements": 3,
"container_id": 1,
"belongsTo": "ID_3c9218a4-31f0-4371-8554-2e8a0a7db97e",
"calls": "ID_51a6dbb1-ff2f-4cd3-bfa7-129e6e151886",
"calledBy": "ID_51a6dbb1-ff2f-4cd3-bfa7-129e6e151886",
"signature": ""
},{
"id": "ID_51a6dbb1-ff2f-4cd3-bfa7-129e6e151886",
"qualifiedName": "/GISA/CCLM./GISA/CCLMT./GISA/CCLMT_CROSSREF_TEST./GISA/CL_CCLMT_CR_TEST_CLASS01.LOOP_METHOD02",
"name": "LOOP_METHOD02",
"abap_type": "METH",
"type": "Method",
"creator": "GPRA437",
"created": 20200915,
"changed_by": "GPRA587",
"changed": 20220110,
"iteration": 0,
"number_of_statements": 3,
"container_id": 1,
"belongsTo": "ID_3c9218a4-31f0-4371-8554-2e8a0a7db97e",
"calls": "ID_4af5f5bf-41ec-431c-9cec-16f8fafad58a",
"calledBy": "ID_4af5f5bf-41ec-431c-9cec-16f8fafad58a",
"signature": ""
},{
"id": "ID_582ac1ba-6e9c-4e86-afbc-dc6dabd411cd",
"qualifiedName": "/GISA/CCLM./GISA/CCLMT./GISA/CCLMT_CROSSREF_TEST./GISA/CCLMT_TEST_FUGR01./GISA/CCLMT_TEST_PAI_INCLUDE",
"name": "/GISA/CCLMT_TEST_PAI_INCLUDE",
"abap_type": "FUNC",
"type": "FunctionModule",
"creator": "GPRA587",
"created": 20220303,
"changed_by": "GPRA587",
"changed": 20220303,
"iteration": 0,
"number_of_statements": 3,
"container_id": 64,
"belongsTo": "ID_5e5da62b-6547-44e7-946f-e7b5d6b64007"
},{
"id": "ID_5d8abefd-73b3-4ab0-97af-ba3c91a80d92",
"qualifiedName": "/GISA/CCLM./GISA/CCLMT./GISA/CCLMT_CROSSREF_TEST./GISA/CCLMT_TEST_FUGR01./GISA/CCLMT_TEST_LOCAL_CLASS",
"name": "/GISA/CCLMT_TEST_LOCAL_CLASS",
"abap_type": "FUNC",
"type": "FunctionModule",
"creator": "GPRA587",
"created": 20220303,
"changed_by": "GPRA587",
"changed": 20220303,
"iteration": 0,
"number_of_statements": 3,
"container_id": 64,
"belongsTo": "ID_5e5da62b-6547-44e7-946f-e7b5d6b64007"
},{
"id": "ID_5e5da62b-6547-44e7-946f-e7b5d6b64007",
"qualifiedName": "/GISA/CCLM./GISA/CCLMT./GISA/CCLMT_CROSSREF_TEST./GISA/CCLMT_TEST_FUGR01",
"name": "/GISA/CCLMT_TEST_FUGR01",
"abap_type": "FUGR",
"type": "FunctionGroup",
"creator": "GPRA437",
"created": 20201202,
"iteration": 0,
"container_id": 2,
"belongsTo": "ID_76417dc0-9f5e-484f-b6ef-91c6ec617092",
"calls": "",
"calledBy": ""
},{
"id": "ID_5f0fe544-4060-4faa-a0a2-e9849351bd5f",
"qualifiedName": "/GISA/CCLM./GISA/CCLMT./GISA/CCLMT_CROSSREF_TEST./GISA/CCLMT_TEST_FUGR01./GISA/CCLMT_TEST_FUBA01",
"name": "/GISA/CCLMT_TEST_FUBA01",
"abap_type": "FUNC",
"type": "FunctionModule",
"creator": "GPRA437",
"created": 20201202,
"changed_by": "GPRA587",
"changed": 20220303,
"iteration": 0,
"number_of_statements": 3,
"container_id": 64,
"belongsTo": "ID_5e5da62b-6547-44e7-946f-e7b5d6b64007"
},{
"id": "ID_6254a969-cfe5-4969-a2dc-e6f72d863cf4",
"qualifiedName": "/GISA/CCLM./GISA/CCLMT./GISA/CCLMT_CROSSREF_TEST./GISA/CCLMT_CR_TEST_REPORT_01",
"name": "/GISA/CCLMT_CR_TEST_REPORT_01",
"abap_type": "REPS",
"type": "Report",
"creator": "GPRA437",
"created": 20200915,
"changed_by": "GPRA437",
"changed": 20210407,
"iteration": 0,
"number_of_statements": 8,
"container_id": 2,
"belongsTo": "ID_76417dc0-9f5e-484f-b6ef-91c6ec617092",
"calls": "ID_d14d053b-b686-4683-ac06-19a4a76b6560, ID_23a16a9a-9d4b-406a-84a9-e344c2bde655, ID_5f0fe544-4060-4faa-a0a2-e9849351bd5f, ID_3c9218a4-31f0-4371-8554-2e8a0a7db97e",
"calledBy": ""
},{
"id": "ID_62ed4cf4-eaae-4cdf-a9ad-554aa27b1761",
"qualifiedName": "/GISA/CCLM./GISA/CCLMT./GISA/CCLMT_CROSSREF_TEST./GISA/CL_CCLMT_CR_TEST_CLASS01.TEST_METHOD04",
"name": "TEST_METHOD04",
"abap_type": "METH",
"type": "Method",
"creator": "GPRA437",
"created": 20200915,
"changed_by": "GPRA587",
"changed": 20220110,
"iteration": 0,
"number_of_statements": 1,
"container_id": 1,
"belongsTo": "ID_3c9218a4-31f0-4371-8554-2e8a0a7db97e",
"calls": "ID_add55f0a-0cf5-4f1f-889a-065c36a5edf9",
"calledBy": "ID_ae5d7e34-3425-4a8b-b1d2-74f290b58f27",
"signature": ""
},{
"id": "ID_6a5fe2f1-ea64-4efd-9341-6f651d9fbe29",
"qualifiedName": "LCL_WIND.RECITE",
"name": "RECITE",
"abap_type": "METH",
"type": "Method",
"creator": "GPRA587",
"created": 20220303,
"changed_by": "GPRA587",
"changed": 20220303,
"iteration": 0,
"number_of_statements": 3,
"container_id": 121,
"belongsTo": "ID_267b8871-93bf-4ff9-ad17-ca1c78e0ee73",
"calls": "ID_5d8abefd-73b3-4ab0-97af-ba3c91a80d92",
"calledBy": "",
"signature": ""
},{
"id": "ID_6c7e4196-d4cc-4cbe-923b-a1c717569219",
"qualifiedName": "/GISA/CCLM./GISA/CCLMT./GISA/CCLMT_CROSSREF_TEST./GISA/CCLMT_FORM_FUBA",
"name": "/GISA/CCLMT_FORM_FUBA",
"abap_type": "REPS",
"type": "Report",
"creator": "GPRA587",
"created": 20220303,
"changed_by": "GPRA587",
"changed": 20220303,
"iteration": 0,
"number_of_statements": 0,
"container_id": 2,
"belongsTo": "ID_76417dc0-9f5e-484f-b6ef-91c6ec617092",
"calls": "ID_5f0fe544-4060-4faa-a0a2-e9849351bd5f, ID_5d8abefd-73b3-4ab0-97af-ba3c91a80d92, ID_582ac1ba-6e9c-4e86-afbc-dc6dabd411cd",
"calledBy": "ID_ac2c3b89-1b09-4ac9-aacc-557a3604efc7"
},{
"id": "ID_6dc6d9e6-4853-47c3-a8e9-5cf62c28394a",
"qualifiedName": "/GISA/CCLM./GISA/CCLMT./GISA/CCLMT_CROSSREF_TEST./GISA/CL_CCLMT_CR_TEST_CLASS01.TEST_METHOD07",
"name": "TEST_METHOD07",
"abap_type": "METH",
"type": "Method",
"creator": "GPRA437",
"created": 20200915,
"changed_by": "GPRA587",
"changed": 20220110,
"iteration": 0,
"number_of_statements": 2,
"container_id": 1,
"belongsTo": "ID_3c9218a4-31f0-4371-8554-2e8a0a7db97e",
"calls": "",
"calledBy": "ID_061e8f94-a038-4092-bd15-be9a8ff6a78a",
"signature": ""
},{
"id": "ID_6f96551a-1997-41c7-a300-aa80dba46fa3",
"qualifiedName": "/GISA/CCLM./GISA/CCLMT./GISA/CCLMT_CROSSREF_TEST./GISA/CCLMT_CR_TEST_REPORT_01.LO_TEST",
"name": "LO_TEST",
"abap_type": "ATTR",
"type": "Attribute",
"creator": "GPRA437",
"created": 20200915,
"changed_by": "GPRA437",
"changed": 20210407,
"iteration": 0,
"container_id": 72,
"belongsTo": "ID_6254a969-cfe5-4969-a2dc-e6f72d863cf4"
},{
"id": "ID_6f9696a7-c24e-40b0-9a59-27dd7c37ef54",
"qualifiedName": "/GISA/CCLM./GISA/CCLMT./GISA/CCLMT_CROSSREF_TEST./GISA/CL_CCLMT_CR_TEST_CLASS03.DYNAMIC_TEST_METHOD08",
"name": "DYNAMIC_TEST_METHOD08",
"abap_type": "METH",
"type": "Method",
"creator": "GPRA437",
"created": 20201117,
"changed_by": "GPRA437",
"changed": 20201202,
"iteration": 0,
"number_of_statements": 2,
"container_id": 41,
"belongsTo": "ID_7f8d04ed-63ba-45c9-8146-8034ffde21ae",
"calls": "",
"calledBy": "",
"signature": ""
},{
"id": "ID_6faa7174-67a4-46fd-8d44-49f1da443e2b",
"qualifiedName": "/GISA/CCLM./GISA/CCLMT./GISA/CCLMT_CROSSREF_TEST./GISA/CCLMT_CR_TEST_REPORT_02",
"name": "/GISA/CCLMT_CR_TEST_REPORT_02",
"abap_type": "REPS",
"type": "Report",
"creator": "GPRA437",
"created": 20200915,
"changed_by": "GPRA437",
"changed": 20200915,
"iteration": 0,
"number_of_statements": 3,
"container_id": 2,
"belongsTo": "ID_0190be5d-a551-4890-b34e-5ce7817c6816",
"calls": "ID_d14d053b-b686-4683-ac06-19a4a76b6560, ID_3c9218a4-31f0-4371-8554-2e8a0a7db97e",
"calledBy": ""
},{
"id": "ID_6ffa33c9-a5ca-464f-9edc-4ab9c66ca823",
"qualifiedName": "/GISA/CCLM./GISA/CCLMT./GISA/CCLMT_CROSSREF_TEST./GISA/CL_CCLMT_CR_TEST_CLASS03.DYNAMIC_TEST_METHOD06",
"name": "DYNAMIC_TEST_METHOD06",
"abap_type": "METH",
"type": "Method",
"creator": "GPRA437",
"created": 20201117,
"changed_by": "GPRA437",
"changed": 20201202,
"iteration": 0,
"number_of_statements": 5,
"container_id": 41,
"belongsTo": "ID_7f8d04ed-63ba-45c9-8146-8034ffde21ae",
"calls": "ID_c6c58ab4-ad16-4c87-9c87-fe229d3b0f1c",
"calledBy": "",
"signature": ""
},{
"id": "ID_755e8ba0-a3bf-489b-8ee5-745723d6bf91",
"qualifiedName": "/GISA/CCLM./GISA/CCLMT./GISA/CCLMT_CROSSREF_TEST./GISA/CL_CCLMT_CR_TEST_CLASS03./GISA/IF_CCLMT_CR_TEST_IF01~TEST_INTERFACE_METHOD",
"name": "/GISA/IF_CCLMT_CR_TEST_IF01~TEST_INTERFACE_METHOD",
"abap_type": "METH",
"type": "Method",
"creator": "GPRA437",
"created": 20201117,
"changed_by": "GPRA437",
"changed": 20201202,
"iteration": 0,
"number_of_statements": 3,
"container_id": 41,
"belongsTo": "ID_7f8d04ed-63ba-45c9-8146-8034ffde21ae",
"calls": "ID_8bd74bd8-b060-421f-8204-18908897c791",
"calledBy": "ID_e5786145-dca9-466d-a852-2a0ff08c6fb1",
"signature": ""
},{
"id": "ID_76417dc0-9f5e-484f-b6ef-91c6ec617092",
"qualifiedName": "/GISA/CCLM./GISA/CCLMT./GISA/CCLMT_CROSSREF_TEST",
"name": "/GISA/CCLMT_CROSSREF_TEST",
"abap_type": "DEVC",
"type": "Namespace",
"creator": "GPRA437",
"created": 20200915,
"changed_by": "GPRA437",
"changed": 20200915,
"iteration": 0,
"container_id": 110
},{
"id": "ID_7f8d04ed-63ba-45c9-8146-8034ffde21ae",
"qualifiedName": "/GISA/CCLM./GISA/CCLMT./GISA/CCLMT_CROSSREF_TEST./GISA/CL_CCLMT_CR_TEST_CLASS03",
"name": "/GISA/CL_CCLMT_CR_TEST_CLASS03",
"abap_type": "CLAS",
"type": "Class",
"creator": "GPRA437",
"created": 20201117,
"changed_by": "GPRA437",
"changed": 20201202,
"iteration": 0,
"local_class": "false",
"container_id": 2,
"belongsTo": "ID_76417dc0-9f5e-484f-b6ef-91c6ec617092",
"subClassOf": "",
"superClassOf": ""
},{
"id": "ID_833870c4-0dd8-4575-86f6-b277b6a35220",
"qualifiedName": "/GISA/CCLM./GISA/CCLMT./GISA/CCLMT_CROSSREF_TEST./GISA/CL_CCLMT_CR_TEST_CLASS01.RECURSIVE_METHOD01",
"name": "RECURSIVE_METHOD01",
"abap_type": "METH",
"type": "Method",
"creator": "GPRA437",
"created": 20200915,
"changed_by": "GPRA587",
"changed": 20220110,
"iteration": 0,
"number_of_statements": 3,
"container_id": 1,
"belongsTo": "ID_3c9218a4-31f0-4371-8554-2e8a0a7db97e",
"calls": "ID_833870c4-0dd8-4575-86f6-b277b6a35220",
"calledBy": "ID_833870c4-0dd8-4575-86f6-b277b6a35220",
"signature": ""
},{
"id": "ID_867df4dd-049e-49b0-a557-010a64764ab1",
"qualifiedName": "/GISA/CCLM./GISA/CCLMT./GISA/CCLMT_CROSSREF_TEST./GISA/CL_CCLMT_CR_TEST_CLASS01.TEST_METHOD03",
"name": "TEST_METHOD03",
"abap_type": "METH",
"type": "Method",
"creator": "GPRA437",
"created": 20200915,
"changed_by": "GPRA587",
"changed": 20220110,
"iteration": 0,
"number_of_statements": 2,
"container_id": 1,
"belongsTo": "ID_3c9218a4-31f0-4371-8554-2e8a0a7db97e",
"calls": "",
"calledBy": "",
"signature": ""
},{
"id": "ID_8bd74bd8-b060-421f-8204-18908897c791",
"qualifiedName": "/GISA/CCLM./GISA/CCLMT./GISA/CCLMT_CROSSREF_TEST./GISA/CL_CCLMT_CR_TEST_CLASS01./GISA/IF_CCLMT_CR_TEST_IF01~TEST_INTERFACE_METHOD",
"name": "/GISA/IF_CCLMT_CR_TEST_IF01~TEST_INTERFACE_METHOD",
"abap_type": "METH",
"type": "Method",
"creator": "GPRA437",
"created": 20200915,
"changed_by": "GPRA587",
"changed": 20220110,
"iteration": 0,
"number_of_statements": 3,
"container_id": 1,
"belongsTo": "ID_3c9218a4-31f0-4371-8554-2e8a0a7db97e",
"calls": "",
"calledBy": "ID_755e8ba0-a3bf-489b-8ee5-745723d6bf91, ID_e5786145-dca9-466d-a852-2a0ff08c6fb1",
"signature": ""
},{
"id": "ID_9207f663-a8e1-4c5f-bf39-1e64cf5cdc9f",
"qualifiedName": "/GISA/CCLM./GISA/CCLMT./GISA/CCLMT_CROSSREF_TEST./GISA/CL_CCLMT_CR_TEST_CLASS03.DYNAMIC_TEST_METHOD01",
"name": "DYNAMIC_TEST_METHOD01",
"abap_type": "METH",
"type": "Method",
"creator": "GPRA437",
"created": 20201117,
"changed_by": "GPRA437",
"changed": 20201202,
"iteration": 0,
"number_of_statements": 1,
"container_id": 41,
"belongsTo": "ID_7f8d04ed-63ba-45c9-8146-8034ffde21ae",
"calls": "ID_d14d053b-b686-4683-ac06-19a4a76b6560",
"calledBy": "",
"signature": ""
},{
"id": "ID_947741f1-5271-4d62-b93f-af6c01a52718",
"qualifiedName": "/GISA/CCLM./GISA/CCLMT./GISA/CCLMT_CROSSREF_TEST./GISA/CCLMT_CR_TEST_REPORT_04",
"name": "/GISA/CCLMT_CR_TEST_REPORT_04",
"abap_type": "REPS",
"type": "Report",
"creator": "GPRA437",
"created": 20201009,
"changed_by": "GPRA437",
"changed": 20201009,
"iteration": 0,
"number_of_statements": 3,
"container_id": 2,
"belongsTo": "ID_76417dc0-9f5e-484f-b6ef-91c6ec617092",
"calls": "ID_add55f0a-0cf5-4f1f-889a-065c36a5edf9, ID_3c9218a4-31f0-4371-8554-2e8a0a7db97e",
"calledBy": ""
},{
"id": "ID_9717cf08-3fc7-4962-811a-ce7bf77cb6e0",
"qualifiedName": "/GISA/CCLM./GISA/CCLMT./GISA/CCLMT_CROSSREF_TEST./GISA/CL_CCLMT_CR_TEST_CLASS01.NOT_QUITE_SO_LONG_TEST_METHOD",
"name": "NOT_QUITE_SO_LONG_TEST_METHOD",
"abap_type": "METH",
"type": "Method",
"creator": "GPRA437",
"created": 20200915,
"changed_by": "GPRA587",
"changed": 20220110,
"iteration": 0,
"number_of_statements": 1,
"container_id": 1,
"belongsTo": "ID_3c9218a4-31f0-4371-8554-2e8a0a7db97e",
"calls": "ID_cabd2699-e3bc-41a7-bc45-4edbd9281be8",
"calledBy": "ID_bf2cf88c-a7a5-4230-812b-d1e6a2c0901a",
"signature": ""
},{
"id": "ID_a001ca96-7349-4185-bece-5401e1fca2be",
"qualifiedName": "/GISA/CCLM./GISA/CCLMT./GISA/CCLMT_CROSSREF_TEST./GISA/CCLMT_TEST_SAP",
"name": "/GISA/CCLMT_TEST_SAP",
"abap_type": "FUGR",
"type": "FunctionGroup",
"creator": "GPRA587",
"created": 20220530,
"iteration": 0,
"container_id": 2,
"belongsTo": "ID_76417dc0-9f5e-484f-b6ef-91c6ec617092",
"calls": "",
"calledBy": ""
},{
"id": "ID_a1c3614a-bb8c-4d14-87ba-35bf8cf3a2dc",
"qualifiedName": "/GISA/CCLM./GISA/CCLMT./GISA/CCLMT_CROSSREF_TEST./GISA/CCLMT_INCLUDE_TEST.HELLO_WORLD",
"name": "HELLO_WORLD",
"abap_type": "FORM",
"type": "FormRoutine",
"creator": "GPRA587",
"created": 20220303,
"changed_by": "GPRA587",
"changed": 20220303,
"iteration": 0,
"number_of_statements": 1,
"container_id": 100,
"belongsTo": "ID_ac399c5c-3623-4cc4-b06b-f1636b057403",
"calls": "ID_5f0fe544-4060-4faa-a0a2-e9849351bd5f",
"calledBy": "ID_ac2c3b89-1b09-4ac9-aacc-557a3604efc7"
},{
"id": "ID_a3441137-d4bf-460f-bd9b-173b5ec4f981",
"qualifiedName": "/GISA/CCLM./GISA/CCLMT./GISA/CCLMT_CROSSREF_TEST./GISA/CCLMT_CR_TEST_REPORT_01.LV_FUBA_NAME",
"name": "LV_FUBA_NAME",
"abap_type": "ATTR",
"type": "Attribute",
"creator": "GPRA437",
"created": 20200915,
"changed_by": "GPRA437",
"changed": 20210407,
"iteration": 0,
"container_id": 72,
"belongsTo": "ID_6254a969-cfe5-4969-a2dc-e6f72d863cf4"
},{
"id": "ID_a60efb94-c3f5-43b9-8af8-48778718e825",
"qualifiedName": "/GISA/CCLM./GISA/CCLMT./GISA/CCLMT_CROSSREF_TEST./GISA/CCLMT_CR_TEST_REPORT_05",
"name": "/GISA/CCLMT_CR_TEST_REPORT_05",
"abap_type": "REPS",
"type": "Report",
"creator": "GPRA437",
"created": 20201009,
"changed_by": "GPRA437",
"changed": 20201009,
"iteration": 0,
"number_of_statements": 3,
"container_id": 2,
"belongsTo": "ID_76417dc0-9f5e-484f-b6ef-91c6ec617092",
"calls": "ID_62ed4cf4-eaae-4cdf-a9ad-554aa27b1761, ID_3c9218a4-31f0-4371-8554-2e8a0a7db97e",
"calledBy": ""
},{
"id": "ID_a6c3c4d2-751e-4193-b2d6-d42742e9262b",
"qualifiedName": "/GISA/CCLM./GISA/CCLMT./GISA/CCLMT_CROSSREF_TEST./GISA/CL_CCLMT_CR_TEST_CLASS01.TEST_METHOD_WITH_PARAMETERS",
"name": "TEST_METHOD_WITH_PARAMETERS",
"abap_type": "METH",
"type": "Method",
"creator": "GPRA437",
"created": 20200915,
"changed_by": "GPRA587",
"changed": 20220110,
"iteration": 0,
"number_of_statements": 2,
"container_id": 1,
"belongsTo": "ID_3c9218a4-31f0-4371-8554-2e8a0a7db97e",
"calls": "",
"calledBy": "ID_275d6dab-bbb1-4740-8fc9-2b95fe23942c",
"signature": ""
},{
"id": "ID_ac2c3b89-1b09-4ac9-aacc-557a3604efc7",
"qualifiedName": "/GISA/CCLM./GISA/CCLMT./GISA/CCLMT_CROSSREF_TEST./GISA/CCLMT_INCLUDE_TEST",
"name": "/GISA/CCLMT_INCLUDE_TEST",
"abap_type": "REPS",
"type": "Report",
"creator": "GPRA587",
"created": 20220303,
"changed_by": "GPRA587",
"changed": 20220303,
"iteration": 0,
"number_of_statements": 5,
"container_id": 2,
"belongsTo": "ID_ac399c5c-3623-4cc4-b06b-f1636b057403",
"calls": "ID_a1c3614a-bb8c-4d14-87ba-35bf8cf3a2dc, ID_c028ceba-dac6-4092-b17e-b10ba03425eb, ID_ec7fc263-4df6-4d5d-b142-25234b9e6cc5",
"calledBy": ""
},{
"id": "ID_ac399c5c-3623-4cc4-b06b-f1636b057403",
"qualifiedName": "/GISA/CCLM./GISA/CCLMT./GISA/CCLMT_CROSSREF_TEST./GISA/CCLMT_INCLUDE_TEST",
"name": "/GISA/CCLMT_INCLUDE_TEST",
"abap_type": "REPS",
"type": "Report",
"creator": "GPRA587",
"created": 20220303,
"changed_by": "GPRA587",
"changed": 20220303,
"iteration": 0,
"number_of_statements": 5,
"container_id": 2,
"belongsTo": "ID_76417dc0-9f5e-484f-b6ef-91c6ec617092",
"calls": "ID_a1c3614a-bb8c-4d14-87ba-35bf8cf3a2dc, ID_c028ceba-dac6-4092-b17e-b10ba03425eb, ID_ec7fc263-4df6-4d5d-b142-25234b9e6cc5",
"calledBy": ""
},{
"id": "ID_add55f0a-0cf5-4f1f-889a-065c36a5edf9",
"qualifiedName": "/GISA/CCLM./GISA/CCLMT./GISA/CCLMT_CROSSREF_TEST./GISA/CL_CCLMT_CR_TEST_CLASS01.TEST_METHOD05",
"name": "TEST_METHOD05",
"abap_type": "METH",
"type": "Method",
"creator": "GPRA437",
"created": 20200915,
"changed_by": "GPRA587",
"changed": 20220110,
"iteration": 0,
"number_of_statements": 2,
"container_id": 1,
"belongsTo": "ID_3c9218a4-31f0-4371-8554-2e8a0a7db97e",
"calls": "ID_061e8f94-a038-4092-bd15-be9a8ff6a78a, ID_aec3e38b-d9d5-498a-8da6-071036c239d5",
"calledBy": "ID_62ed4cf4-eaae-4cdf-a9ad-554aa27b1761, ID_b5bf56f8-c07a-49d8-b12b-11ba89e6a4ab",
"signature": ""
},{
"id": "ID_ae188004-94a4-44da-81a0-afd09985bcf8",
"qualifiedName": "/GISA/CCLM./GISA/CCLMT./GISA/CCLMT_CROSSREF_TEST./GISA/CCLMT_CR_TEST_REPORT_02.LO_TEST",
"name": "LO_TEST",
"abap_type": "ATTR",
"type": "Attribute",
"creator": "GPRA437",
"created": 20200915,
"changed_by": "GPRA437",
"changed": 20200915,
"iteration": 0,
"container_id": 82,
"belongsTo": "ID_0190be5d-a551-4890-b34e-5ce7817c6816"
},{
"id": "ID_ae5d7e34-3425-4a8b-b1d2-74f290b58f27",
"qualifiedName": "/GISA/CCLM./GISA/CCLMT./GISA/CCLMT_CROSSREF_TEST./GISA/CCLMT_CR_TEST_REPORT_05",
"name": "/GISA/CCLMT_CR_TEST_REPORT_05",
"abap_type": "REPS",
"type": "Report",
"creator": "GPRA437",
"created": 20201009,
"changed_by": "GPRA437",
"changed": 20201009,
"iteration": 0,
"number_of_statements": 3,
"container_id": 2,
"belongsTo": "ID_a60efb94-c3f5-43b9-8af8-48778718e825",
"calls": "ID_62ed4cf4-eaae-4cdf-a9ad-554aa27b1761, ID_3c9218a4-31f0-4371-8554-2e8a0a7db97e",
"calledBy": ""
},{
"id": "ID_aec3e38b-d9d5-498a-8da6-071036c239d5",
"qualifiedName": "/GISA/CCLM./GISA/CCLMT./GISA/CCLMT_CROSSREF_TEST./GISA/CL_CCLMT_CR_TEST_CLASS01.TEST_METHOD08",
"name": "TEST_METHOD08",
"abap_type": "METH",
"type": "Method",
"creator": "GPRA437",
"created": 20200915,
"changed_by": "GPRA587",
"changed": 20220110,
"iteration": 0,
"number_of_statements": 2,
"container_id": 1,
"belongsTo": "ID_3c9218a4-31f0-4371-8554-2e8a0a7db97e",
"calls": "",
"calledBy": "ID_add55f0a-0cf5-4f1f-889a-065c36a5edf9",
"signature": ""
},{
"id": "ID_b373abb8-68eb-48aa-a1ae-99c15ad4575a",
"qualifiedName": "/GISA/CCLM./GISA/CCLMT./GISA/CCLMT_CROSSREF_TEST./GISA/CCLMT_FORM_FUBA.HELLO_WORLD",
"name": "HELLO_WORLD",
"abap_type": "FORM",
"type": "FormRoutine",
"creator": "GPRA587",
"created": 20220303,
"changed_by": "GPRA587",
"changed": 20220303,
"iteration": 0,
"number_of_statements": 1,
"container_id": 109,
"belongsTo": "ID_6c7e4196-d4cc-4cbe-923b-a1c717569219",
"calls": "ID_5f0fe544-4060-4faa-a0a2-e9849351bd5f",
"calledBy": ""
},{
"id": "ID_b5bf56f8-c07a-49d8-b12b-11ba89e6a4ab",
"qualifiedName": "/GISA/CCLM./GISA/CCLMT./GISA/CCLMT_CROSSREF_TEST./GISA/CCLMT_CR_TEST_REPORT_04",
"name": "/GISA/CCLMT_CR_TEST_REPORT_04",
"abap_type": "REPS",
"type": "Report",
"creator": "GPRA437",
"created": 20201009,
"changed_by": "GPRA437",
"changed": 20201009,
"iteration": 0,
"number_of_statements": 3,
"container_id": 2,
"belongsTo": "ID_947741f1-5271-4d62-b93f-af6c01a52718",
"calls": "ID_add55f0a-0cf5-4f1f-889a-065c36a5edf9, ID_3c9218a4-31f0-4371-8554-2e8a0a7db97e",
"calledBy": ""
},{
"id": "ID_b70d801e-012a-4a1c-b0a2-7f79c420343a",
"qualifiedName": "/GISA/CCLM./GISA/CCLMT./GISA/CCLMT_CROSSREF_TEST./GISA/CCLMT_TEST_SAP./GISA/CCLMT_TEST_INTERSECTION",
"name": "/GISA/CCLMT_TEST_INTERSECTION",
"abap_type": "FUNC",
"type": "FunctionModule",
"creator": "GPRA587",
"created": 20220530,
"changed_by": "GPRA587",
"changed": 20220530,
"iteration": 0,
"number_of_statements": 2,
"container_id": 68,
"belongsTo": "ID_a001ca96-7349-4185-bece-5401e1fca2be"
},{
"id": "ID_bf2cf88c-a7a5-4230-812b-d1e6a2c0901a",
"qualifiedName": "/GISA/CCLM./GISA/CCLMT./GISA/CCLMT_CROSSREF_TEST./GISA/CL_CCLMT_CR_TEST_CLASS01.REALLY_REALLY_LONG_TEST_METHOD",
"name": "REALLY_REALLY_LONG_TEST_METHOD",
"abap_type": "METH",
"type": "Method",
"creator": "GPRA437",
"created": 20200915,
"changed_by": "GPRA587",
"changed": 20220110,
"iteration": 0,
"number_of_statements": 1,
"container_id": 1,
"belongsTo": "ID_3c9218a4-31f0-4371-8554-2e8a0a7db97e",
"calls": "ID_9717cf08-3fc7-4962-811a-ce7bf77cb6e0",
"calledBy": "ID_cabd2699-e3bc-41a7-bc45-4edbd9281be8",
"signature": ""
},{
"id": "ID_bfb0b45b-1916-40ab-97fe-0afdc8e8890d",
"qualifiedName": "/GISA/CCLM./GISA/CCLMT./GISA/CCLMT_CROSSREF_TEST./GISA/CL_CCLMT_CR_TEST_CLASS02",
"name": "/GISA/CL_CCLMT_CR_TEST_CLASS02",
"abap_type": "CLAS",
"type": "Class",
"creator": "GPRA437",
"created": 20200916,
"changed_by": "GPRA437",
"changed": 20200916,
"iteration": 0,
"local_class": "false",
"container_id": 2,
"belongsTo": "ID_76417dc0-9f5e-484f-b6ef-91c6ec617092",
"subClassOf": "",
"superClassOf": ""
},{
"id": "ID_c028ceba-dac6-4092-b17e-b10ba03425eb",
"qualifiedName": "/GISA/CCLM./GISA/CCLMT./GISA/CCLMT_CROSSREF_TEST./GISA/CCLMT_FORM_FUBA",
"name": "/GISA/CCLMT_FORM_FUBA",
"abap_type": "REPS",
"type": "Report",
"creator": "GPRA587",
"created": 20220303,
"changed_by": "GPRA587",
"changed": 20220303,
"iteration": 0,
"number_of_statements": 0,
"container_id": 2,
"belongsTo": "ID_6c7e4196-d4cc-4cbe-923b-a1c717569219",
"calls": "ID_5f0fe544-4060-4faa-a0a2-e9849351bd5f, ID_5d8abefd-73b3-4ab0-97af-ba3c91a80d92, ID_582ac1ba-6e9c-4e86-afbc-dc6dabd411cd",
"calledBy": "ID_ac2c3b89-1b09-4ac9-aacc-557a3604efc7"
},{
"id": "ID_c2acfeb6-2590-4556-8da3-33332dc0c8b1",
"qualifiedName": "/GISA/CCLM./GISA/CCLMT./GISA/CCLMT_CROSSREF_TEST./GISA/CL_CCLMT_CR_TEST_CLASS02.LO_TESTCLASS01",
"name": "LO_TESTCLASS01",
"abap_type": "ATTR",
"type": "Attribute",
"creator": "GPRA437",
"created": 20200916,
"changed_by": "GPRA437",
"changed": 20200916,
"iteration": 0,
"container_id": 39,
"belongsTo": "ID_bfb0b45b-1916-40ab-97fe-0afdc8e8890d"
},{
"id": "ID_c6c58ab4-ad16-4c87-9c87-fe229d3b0f1c",
"qualifiedName": "/GISA/CCLM./GISA/CCLMT./GISA/CCLMT_CROSSREF_TEST./GISA/CL_CCLMT_CR_TEST_CLASS01.TEST_METHOD_WITH_PARAMETERS2",
"name": "TEST_METHOD_WITH_PARAMETERS2",
"abap_type": "METH",
"type": "Method",
"creator": "GPRA437",
"created": 20200915,
"changed_by": "GPRA587",
"changed": 20220110,
"iteration": 0,
"number_of_statements": 3,
"container_id": 1,
"belongsTo": "ID_3c9218a4-31f0-4371-8554-2e8a0a7db97e",
"calls": "",
"calledBy": "ID_4a02540f-5d15-4200-88e2-b35c51feb5fb, ID_6ffa33c9-a5ca-464f-9edc-4ab9c66ca823",
"signature": ""
},{
"id": "ID_cabd2699-e3bc-41a7-bc45-4edbd9281be8",
"qualifiedName": "/GISA/CCLM./GISA/CCLMT./GISA/CCLMT_CROSSREF_TEST./GISA/CL_CCLMT_CR_TEST_CLASS01.TEST_METHOD09",
"name": "TEST_METHOD09",
"abap_type": "METH",
"type": "Method",
"creator": "GPRA437",
"created": 20200915,
"changed_by": "GPRA587",
"changed": 20220110,
"iteration": 0,
"number_of_statements": 1,
"container_id": 1,
"belongsTo": "ID_3c9218a4-31f0-4371-8554-2e8a0a7db97e",
"calls": "ID_bf2cf88c-a7a5-4230-812b-d1e6a2c0901a",
"calledBy": "ID_9717cf08-3fc7-4962-811a-ce7bf77cb6e0",
"signature": ""
},{
"id": "ID_cd1b1302-6b4a-4714-bfa5-a841c30baa75",
"qualifiedName": "/GISA/CCLM./GISA/CCLMT./GISA/CCLMT_CROSSREF_TEST./GISA/CCLMT_CR_TEST_REPORT_05.LO_TEST",
"name": "LO_TEST",
"abap_type": "ATTR",
"type": "Attribute",
"creator": "GPRA437",
"created": 20201009,
"changed_by": "GPRA437",
"changed": 20201009,
"iteration": 0,
"container_id": 95,
"belongsTo": "ID_a60efb94-c3f5-43b9-8af8-48778718e825"
},{
"id": "ID_d14d053b-b686-4683-ac06-19a4a76b6560",
"qualifiedName": "/GISA/CCLM./GISA/CCLMT./GISA/CCLMT_CROSSREF_TEST./GISA/CL_CCLMT_CR_TEST_CLASS01.TEST_METHOD01",
"name": "TEST_METHOD01",
"abap_type": "METH",
"type": "Method",
"creator": "GPRA437",
"created": 20200915,
"changed_by": "GPRA587",
"changed": 20220110,
"iteration": 0,
"number_of_statements": 2,
"container_id": 1,
"belongsTo": "ID_3c9218a4-31f0-4371-8554-2e8a0a7db97e",
"calls": "",
"calledBy": "ID_e30bc010-ada2-4a9a-b8a9-16bb5f9facb0, ID_9207f663-a8e1-4c5f-bf39-1e64cf5cdc9f, ID_6faa7174-67a4-46fd-8d44-49f1da443e2b, ID_23a16a9a-9d4b-406a-84a9-e344c2bde655",
"signature": ""
},{
"id": "ID_e30bc010-ada2-4a9a-b8a9-16bb5f9facb0",
"qualifiedName": "/GISA/CCLM./GISA/CCLMT./GISA/CCLMT_CROSSREF_TEST./GISA/CCLMT_CR_TEST_REPORT_01",
"name": "/GISA/CCLMT_CR_TEST_REPORT_01",
"abap_type": "REPS",
"type": "Report",
"creator": "GPRA437",
"created": 20200915,
"changed_by": "GPRA437",
"changed": 20210407,
"iteration": 0,
"number_of_statements": 8,
"container_id": 2,
"belongsTo": "ID_6254a969-cfe5-4969-a2dc-e6f72d863cf4",
"calls": "ID_d14d053b-b686-4683-ac06-19a4a76b6560, ID_23a16a9a-9d4b-406a-84a9-e344c2bde655, ID_5f0fe544-4060-4faa-a0a2-e9849351bd5f, ID_3c9218a4-31f0-4371-8554-2e8a0a7db97e",
"calledBy": ""
},{
"id": "ID_e37de028-afb6-47b7-a85d-75b444a77a77",
"qualifiedName": "/GISA/CCLM./GISA/CCLMT./GISA/CCLMT_CROSSREF_TEST./GISA/CCLMT_CR_TEST_REPORT_04.LO_TEST",
"name": "LO_TEST",
"abap_type": "ATTR",
"type": "Attribute",
"creator": "GPRA437",
"created": 20201009,
"changed_by": "GPRA437",
"changed": 20201009,
"iteration": 0,
"container_id": 90,
"belongsTo": "ID_947741f1-5271-4d62-b93f-af6c01a52718"
},{
"id": "ID_e5786145-dca9-466d-a852-2a0ff08c6fb1",
"qualifiedName": "/GISA/CCLM./GISA/CCLMT./GISA/CCLMT_CROSSREF_TEST./GISA/CL_CCLMT_CR_TEST_CLASS03.DYNAMIC_TEST_METHOD07",
"name": "DYNAMIC_TEST_METHOD07",
"abap_type": "METH",
"type": "Method",
"creator": "GPRA437",
"created": 20201117,
"changed_by": "GPRA437",
"changed": 20201202,
"iteration": 0,
"number_of_statements": 4,
"container_id": 41,
"belongsTo": "ID_7f8d04ed-63ba-45c9-8146-8034ffde21ae",
"calls": "ID_755e8ba0-a3bf-489b-8ee5-745723d6bf91, ID_3c9218a4-31f0-4371-8554-2e8a0a7db97e, ID_8bd74bd8-b060-421f-8204-18908897c791",
"calledBy": "",
"signature": ""
},{
"id": "ID_ec7fc263-4df6-4d5d-b142-25234b9e6cc5",
"qualifiedName": "LCL_WIND.RECITE",
"name": "RECITE",
"abap_type": "METH",
"type": "Method",
"creator": "GPRA587",
"created": 20220303,
"changed_by": "GPRA587",
"changed": 20220303,
"iteration": 0,
"number_of_statements": 3,
"container_id": 101,
"belongsTo": "ID_4126ad2f-d853-4eee-b252-c41999cee2d5",
"calls": "ID_5d8abefd-73b3-4ab0-97af-ba3c91a80d92",
"calledBy": "ID_ac2c3b89-1b09-4ac9-aacc-557a3604efc7",
"signature": ""}]